fck_aws_sso/__init__.py
fck_aws_sso/authorize_sso.py
fck_aws_sso/io.py
fck_aws_sso/main.py
fck_aws_sso-0.2.5.dist-info/METADATA
fck_aws_sso-0.2.5.dist-info/WHEEL
fck_aws_sso-0.2.5.dist-info/entry_points.txt
fck_aws_sso-0.2.5.dist-info/RECORD
