Metadata-Version: 2.1
Name: fck-aws-sso
Version: 0.2.5
Summary: A tool to automate AWS SSO login
Home-page: https://github.com/oskarissimus/fck-aws-sso
Author: Oskar Korczak
Author-email: oskar.korczak@protonmail.com
Requires-Python: >=3.10,<4.0
Classifier: Programming Language :: Python :: 3
Classifier: Programming Language :: Python :: 3.10
Classifier: Programming Language :: Python :: 3.11
Classifier: Programming Language :: Python :: 3.12
Requires-Dist: selenium (>=4.13.0,<5.0.0)
Requires-Dist: typer[all] (>=0.9.0,<0.10.0)
Requires-Dist: webdriver-manager (>=4.0.1,<5.0.0)
Project-URL: Repository, https://github.com/oskarissimus/fck-aws-sso
